pytinytex/__init__.py
pytinytex/tinytex_download.py
PyTinyTeX-0.4.0.dist-info/LICENSE
PyTinyTeX-0.4.0.dist-info/METADATA
PyTinyTeX-0.4.0.dist-info/WHEEL
PyTinyTeX-0.4.0.dist-info/top_level.txt
PyTinyTeX-0.4.0.dist-info/RECORD
